djangorestframework_serializer_mixins-0.1.0.dist-info/DESCRIPTION.rst
djangorestframework_serializer_mixins-0.1.0.dist-info/METADATA
djangorestframework_serializer_mixins-0.1.0.dist-info/RECORD
djangorestframework_serializer_mixins-0.1.0.dist-info/WHEEL
djangorestframework_serializer_mixins-0.1.0.dist-info/metadata.json
djangorestframework_serializer_mixins-0.1.0.dist-info/top_level.txt
rest_framework_serializer_mixins/__init__.py
rest_framework_serializer_mixins/mixins.py
