Metadata-Version: 2.0
Name: djangorestframework-serializer-mixins
Version: 0.1.0
Summary: Mixins for Django Rest Framework Serializer
Home-page: https://github.com/allisson/django-rest-framework-serializer-mixins
Author: Allisson Azevedo
Author-email: allisson@gmail.com
License: UNKNOWN
Keywords: djangorestframework rest
Platform: UNKNOWN
Classifier: Development Status :: 5 - Production/Stable
Classifier: Environment :: Web Environment
Classifier: Framework :: Django
Classifier: Intended Audience :: Developers
Classifier: License :: OSI Approved :: MIT License
Classifier: Operating System :: OS Independent
Classifier: Programming Language :: Python
Classifier: Programming Language :: Python :: 2
Classifier: Programming Language :: Python :: 2.7
Classifier: Programming Language :: Python :: 3
Classifier: Programming Language :: Python :: 3.4
Classifier: Programming Language :: Python :: 3.5
Classifier: Programming Language :: Python :: 3.6
Classifier: Topic :: Internet :: WWW/HTTP
Classifier: Topic :: Software Development :: Libraries :: Application Frameworks
Classifier: Topic :: Software Development :: Libraries :: Python Modules
Requires-Dist: djangorestframework (>=3.5.4)
